incident_io_client/__init__.py
incident_io_client/api/__init__.py
incident_io_client/api/actions_v1/__init__.py
incident_io_client/api/actions_v1/actions_v1_list.py
incident_io_client/api/actions_v1/actions_v1_show.py
incident_io_client/api/actions_v2/__init__.py
incident_io_client/api/actions_v2/actions_v2_list.py
incident_io_client/api/actions_v2/actions_v2_show.py
incident_io_client/api/alert_events_v2/__init__.py
incident_io_client/api/alert_events_v2/alert_events_v2_create_http.py
incident_io_client/api/alert_routes_v2/__init__.py
incident_io_client/api/alert_routes_v2/alert_routes_v2_create.py
incident_io_client/api/alert_routes_v2/alert_routes_v2_destroy.py
incident_io_client/api/alert_routes_v2/alert_routes_v2_show.py
incident_io_client/api/alert_routes_v2/alert_routes_v2_update.py
incident_io_client/api/audit_logs/__init__.py
incident_io_client/api/audit_logs/audit_logs_alert_route_created_v1.py
incident_io_client/api/audit_logs/audit_logs_alert_route_deleted_v1.py
incident_io_client/api/audit_logs/audit_logs_alert_route_updated_v1.py
incident_io_client/api/audit_logs/audit_logs_alert_schema_updated_v1.py
incident_io_client/api/audit_logs/audit_logs_alert_source_config_created_v1.py
incident_io_client/api/audit_logs/audit_logs_alert_source_config_deleted_v1.py
incident_io_client/api/audit_logs/audit_logs_alert_source_config_updated_v1.py
incident_io_client/api/audit_logs/audit_logs_announcement_rule_created_v1.py
incident_io_client/api/audit_logs/audit_logs_announcement_rule_deleted_v1.py
incident_io_client/api/audit_logs/audit_logs_announcement_rule_updated_v1.py
incident_io_client/api/audit_logs/audit_logs_api_key_created_v1.py
incident_io_client/api/audit_logs/audit_logs_api_key_deleted_v1.py
incident_io_client/api/audit_logs/audit_logs_catalog_type_created_v1.py
incident_io_client/api/audit_logs/audit_logs_catalog_type_deleted_v1.py
incident_io_client/api/audit_logs/audit_logs_catalog_type_updated_v1.py
python_incidentio_client-0.56.4.dist-info/LICENSE
python_incidentio_client-0.56.4.dist-info/METADATA
python_incidentio_client-0.56.4.dist-info/WHEEL
python_incidentio_client-0.56.4.dist-info/RECORD
