Metadata-Version: 2.1
Name: python-incidentio-client
Version: 0.56.4
Summary: Python client for Incident.io
Home-page: https://github.com/expobrain/python-incidentio-client
License: MIT
Author: Daniele Esposti
Author-email: daniele.esposti@gmail.com
Requires-Python: >=3.8.1,<4
Classifier: License :: OSI Approved :: MIT License
Classifier: Programming Language :: Python :: 3
Classifier: Programming Language :: Python :: 3.9
Classifier: Programming Language :: Python :: 3.10
Classifier: Programming Language :: Python :: 3.11
Classifier: Programming Language :: Python :: 3.12
Classifier: Programming Language :: Python :: 3.13
Requires-Dist: attrs (>=20.1.0)
Requires-Dist: httpx (>=0.22.0)
Requires-Dist: python-dateutil (>=2.8.0)
Project-URL: Repository, https://github.com/expobrain/python-incidentio-client
